Workbook

Sheet Risk log
A1: Risk Register
A2: Project name: | B2: Glazes Project risks
A3: Project manager: Bob | B3: Jazmyne Kingi
P4: ='Severity Table'!J4 -> Likelihood | Q4: ='Severity Table'!K4 -> 0 | R4: ='Severity Table'!L4 -> 0
P5: ='Severity Table'!J5 -> 1 | Q5: ='Severity Table'!K5 -> 2 | R5: ='Severity Table'!L5 -> 3
A6: ID | B6: Date raised | C6: Risk description | D6: Likelihood of the risk occurring | E6: Impact if the risk occurs | F6: Severity Rating based on impact & likelihood. | G6: Owner Person who will manage the risk. | H6: Mitigating action Actions to mitigate the risk e.g. reduce the likelihood. | I6: Contingent action Action to be taken if the risk happens. | J6: Progress on actions | K6: Status | L6: Useful resources | N6: ='Severity Table'!H6 -> Impact | O6: ='Severity Table'!I6 -> 1 | P6: ='Severity Table'!J6 -> Low | Q6: ='Severity Table'!K6 -> Low | R6: ='Severity Table'!L6 -> Medium
A7: 1 | B7: [start] | C7: Project management, Scope creep, lack of communication, unreseolved conflicts | D7: Low | E7: High | F7: High | G7: Project manager | H7: Implement a formal change control board and daily stand up meetings to ensure clarity. | J7: Business case re-written with clear deliverables and submitted to the project board for approval. | K7: Open | L7: https://elogic.co/blog/ecommerce-project-manager-responsibilities-explained/ | N7: ='Severity Table'!H7 -> 0 | O7: ='Severity Table'!I7 -> 2 | P7: ='Severity Table'!J7 -> Low | Q7: ='Severity Table'!K7 -> Medium | R7: ='Severity Table'!L7 -> High
A8: 2 | B8: [start] | C8: Operational and supply chain, Vendor delays, manufacturing disruptions, logistical bottlenecks | D8: High | E8: High | F8: High | G8: Operations manager, supply chain lead | H8: Diversify vendors to avoid single-point failures and maintain "buffer stick" for critical componets | J8: Design workshops scheduled. | K8: Open | L8: https://www.shipbob.com/blog/ecommerce-operations/ | N8: ='Severity Table'!H8 -> 0 | O8: ='Severity Table'!I8 -> 3 | P8: ='Severity Table'!J8 -> Medium | Q8: ='Severity Table'!K8 -> High | R8: ='Severity Table'!L8 -> High
A9: 3 | B9: [start] | C9: IT and Security, Data breaches, ransomeware and systems outages | D9: Low | E9: High | F9: Medium | G9: IT manager | H9: Deploy multi-factor authentication, regular encrypted back ups and employee phishing training | J9: Workshops scheduled. | K9: Open | L9: https://www.fortinet.com/resources/cyberglossary/it-security
A10: 4 | B10: [enter date] | C10: Finance and compliance, Late tax, international payment and regulatory checks. | D10: High | E10: Low | F10: Medium | G10: Finance manager | H10: Use automated compliance software and enforce segregation of duties for all finacial transactions. | J10: Project Sponsor has agreed to hold briefing. Now making arrangements for a meeting room. | K10: Open | L10: https://www.stakeholdermap.com/project-dictionary/project-dictionary-p.html#project-sponsor
A11: 5 | B11: [enter date] | C11: Human Resources, to anticipate issues such as turn overs, labor disputes or worker shortages. | D11: Low | E11: Medium | F11: High | G11: HR manager CISO | H11: cross-training all team members on critical tasks to ensure informativable. | J11: Lead time from each contractor built into the project schedule. Late penalties agreed to and contracts signed. | K11: Open | L11: https://acquirex.io/blog/human-resource-management-secrets-for-ecommerce-success/
A12: 6 | B12: [enter date] | C12: Eternal threats, Acts of weather, legal action, theift. | D12: High | E12: High | F12: High | G12: Project sponsor | H12: Break this risk into two: 'cost estimating' and 'scheduling errors'. Use two methods of cost estimation, and carefully track costs and forecast cost at completion making adjustments as necessary. Build in 10% contingency on cost and scheduling. Track schedules daily and include schedule review as an agenda item in every project team meeting. Flag forecast errors and/or delays to the Project Board early. | J12: Contingency agreed by Project Board. | K12: Open | L12: https://phoenixnap.com/blog/ecommerce-security-threats

Sheet Severity Table
D3: Likelihood
D4: 1 | E4: 2 | F4: 3 | H4: =B3 -> 0 | I4: =C3 -> 0 | J4: =D3 -> Likelihood | K4: =E3 -> 0 | L4: =F3 -> 0
B5: Impact | C5: 1 | D5: Low | E5: Low | F5: Medium | H5: =B4 -> 0 | I5: =C4 -> 0 | J5: =D4 -> 1 | K5: =E4 -> 2 | L5: =F4 -> 3
C6: 2 | D6: Low | E6: Medium | F6: High | H6: =B5 -> Impact | I6: =C5 -> 1 | J6: =D5 -> Low | K6: =E5 -> Low | L6: =F5 -> Medium
C7: 3 | D7: Medium | E7: High | F7: High | H7: =B6 -> 0 | I7: =C6 -> 2 | J7: =D6 -> Low | K7: =E6 -> Medium | L7: =F6 -> High
H8: =B7 -> 0 | I8: =C7 -> 3 | J8: =D7 -> Medium | K8: =E7 -> High | L8: =F7 -> High

Sheet Dropdowns
B3: Likelihood | C3: Impact | E3: Status
B4: [select] | C4: [select] | E4: Open
B5: High | C5: High | E5: In progress
B6: Medium | C6: Medium | E6: Closed
B7: Low | C7: Low
